cloud2sql/__init__.py
cloud2sql/__main__.py
cloud2sql/collect.py
cloud2sql/util.py
cloud2sql-0.9.0.dist-info/LICENSE
cloud2sql-0.9.0.dist-info/METADATA
cloud2sql-0.9.0.dist-info/WHEEL
cloud2sql-0.9.0.dist-info/entry_points.txt
cloud2sql-0.9.0.dist-info/top_level.txt
cloud2sql-0.9.0.dist-info/RECORD
