Metadata-Version: 2.1
Name: cloud2sql
Version: 0.9.0
Summary: Read infrastructure data from your cloud and export it to a SQL database.
Home-page: https://github.com/someengineering/cloud2sql
License: Apache Software License 2.0
Classifier: Programming Language :: Python :: 3
Requires-Python: >=3.9
License-File: LICENSE
Requires-Dist: SQLAlchemy (==1.4.45)
Requires-Dist: PyYAML (==6.0)
Requires-Dist: rich (==13.4.2)
Requires-Dist: resotoclient (==1.4.1)
Requires-Dist: posthog (==3.0.1)
Requires-Dist: requests (==2.31.0)
Requires-Dist: resotodatalink (==1.0.1)
Requires-Dist: resotolib (==3.5.2)
Requires-Dist: resoto-plugin-aws (==3.5.2)
Requires-Dist: resoto-plugin-digitalocean (==3.5.2)
Requires-Dist: resoto-plugin-gcp (==3.5.2)
Requires-Dist: resoto-plugin-k8s (==3.5.2)
Provides-Extra: all
Requires-Dist: pymysql (>=1.0.2) ; extra == 'all'
Requires-Dist: psycopg2-binary (>=2.9.5) ; extra == 'all'
Requires-Dist: snowflake-sqlalchemy (==1.4.7) ; extra == 'all'
Requires-Dist: pyarrow (==12.0.1) ; extra == 'all'
Requires-Dist: google-cloud-storage (==2.9.0) ; extra == 'all'
Requires-Dist: boto3 (>=1.26.61) ; extra == 'all'
Provides-Extra: mariadb
Requires-Dist: pymysql (>=1.0.2) ; extra == 'mariadb'
Provides-Extra: mysql
Requires-Dist: pymysql (>=1.0.2) ; extra == 'mysql'
Provides-Extra: parquet
Requires-Dist: pyarrow (==12.0.1) ; extra == 'parquet'
Requires-Dist: google-cloud-storage (==2.9.0) ; extra == 'parquet'
Requires-Dist: boto3 (>=1.26.61) ; extra == 'parquet'
Provides-Extra: postgresql
Requires-Dist: psycopg2-binary (>=2.9.5) ; extra == 'postgresql'
Provides-Extra: snowflake
Requires-Dist: snowflake-sqlalchemy (==1.4.7) ; extra == 'snowflake'
